<?xml version="1.0" encoding="UTF-8"?><magicdraw><property classType="Property" humanType="Property" icon="FOM-ReelleRettighetshavere_files/icon_property_213290741.jpg" id="afe81902-3977-4880-9deb-ba0c8d274ab6"><aggregation humanName="Aggregation" mode="s,e">none</aggregation><association classType="Association" humanName="Association" humanType="Association" icon="FOM-ReelleRettighetshavere_files/icon_association_186864538.jpg" isRelationship="true" name="er i posisjon til å" refid="d4bff1e9-5460-4fd3-ac6c-9401a3fd40d2"/><documentation humanName="Documentation"/><featuringClassifier classType="Association" humanName="Featuring Classifier" humanType="Association" icon="FOM-ReelleRettighetshavere_files/icon_association_186864538.jpg" isRelationship="true" name="er i posisjon til å" refid="d4bff1e9-5460-4fd3-ac6c-9401a3fd40d2"/><isComposite humanName="Is Composite">false</isComposite><isDerived humanName="Is Derived" mode="s,e">false</isDerived><isDerivedUnion humanName="Is Derived Union" mode="e">false</isDerivedUnion><isID humanName="Is ID" mode="e">false</isID><isLeaf humanName="Is Leaf">false</isLeaf><isOrdered humanName="Is Ordered" mode="e">false</isOrdered><isReadOnly humanName="Is Read Only" mode="s,e">false</isReadOnly><isStatic humanName="Is Static" mode="s,e">false</isStatic><isUnique humanName="Is Unique" mode="e">true</isUnique><lower humanName="Lower">1</lower><multiplicity humanName="Multiplicity" mode="s,e"/><multiplicity humanName="Multiplicity" mode="s,e"/><name humanName="Name" mode="s,e"/><namespace classType="Association" humanName="Namespace" humanType="Association" icon="FOM-ReelleRettighetshavere_files/icon_association_186864538.jpg" isRelationship="true" name="er i posisjon til å" refid="d4bff1e9-5460-4fd3-ac6c-9401a3fd40d2"/><navigable humanName="Navigable" mode="e">false</navigable><opposite classType="Property" humanName="Opposite" humanType="Property" icon="FOM-ReelleRettighetshavere_files/icon_property_213290741.jpg" name=" : RegisterOverReelleRettighetshavere_fom::Posisjon::Rett til å utpeke et flertall av styremedlemmer" refid="4332e996-2d25-4dca-94f8-a0577b204eff"/><ownedBy classType="Association" humanName="Owned By" humanType="Association" icon="FOM-ReelleRettighetshavere_files/icon_association_186864538.jpg" isRelationship="true" mode="s,e" name="er i posisjon til å" refid="d4bff1e9-5460-4fd3-ac6c-9401a3fd40d2"/><owner classType="Association" humanName="Owner" humanType="Association" icon="FOM-ReelleRettighetshavere_files/icon_association_186864538.jpg" isRelationship="true" name="er i posisjon til å" refid="d4bff1e9-5460-4fd3-ac6c-9401a3fd40d2"/><owningAssociation classType="Association" humanName="Owning Association" humanType="Association" icon="FOM-ReelleRettighetshavere_files/icon_association_186864538.jpg" isRelationship="true" name="er i posisjon til å" refid="d4bff1e9-5460-4fd3-ac6c-9401a3fd40d2"/><qualifiedName humanName="Qualified Name" mode="e">RegisterOverReelleRettighetshavere_fom::ReellRettighetshaver::er i posisjon til å::</qualifiedName><redefinitionContext humanName="Redefinition Context"><association classType="Association" humanType="Association" icon="FOM-ReelleRettighetshavere_files/icon_association_186864538.jpg" isRelationship="true" name="er i posisjon til å" refid="d4bff1e9-5460-4fd3-ac6c-9401a3fd40d2"/></redefinitionContext><TO_DO humanName="To Do" mode="s,e"/><type classType="Class" humanName="Type" humanType="Class" icon="FOM-ReelleRettighetshavere_files/icon_class_951819642.jpg" mode="s,e" name="Reell rettighetshaver" refid="6d1251f1-97e2-4848-b0f4-ae4e326aab4f"/><TYPE_MODIFIER humanName="Type Modifier" mode="e"/><upper humanName="Upper">1</upper><visibility humanName="Visibility" mode="s,e">private</visibility></property></magicdraw>