<?xml version="1.0" encoding="UTF-8"?><magicdraw><property classType="Property" humanType="Property" icon="FOM-ReelleRettighetshavere_files/icon_property_213290741.jpg" id="df075e8b-971e-465d-a9a3-e099c7daa742"><aggregation humanName="Aggregation" mode="s,e">none</aggregation><association classType="Association" humanName="Association" humanType="Association" icon="FOM-ReelleRettighetshavere_files/icon_association_186864538.jpg" isRelationship="true" name="kan være" refid="914420b1-6fac-48d0-8579-8e6db97435f4"/><UMLClass classType="Class" humanName="Class" humanType="Class" icon="FOM-ReelleRettighetshavere_files/icon_class_951819642.jpg" name="Registreringspliktig virksomhet" refid="ef0e2dfc-8346-4803-a917-50ff8895d0f1"/><classifier classType="Class" humanName="Classifier" humanType="Class" icon="FOM-ReelleRettighetshavere_files/icon_class_951819642.jpg" name="Registreringspliktig virksomhet" refid="ef0e2dfc-8346-4803-a917-50ff8895d0f1"/><documentation humanName="Documentation"/><featuringClassifier classType="Class" humanName="Featuring Classifier" humanType="Class" icon="FOM-ReelleRettighetshavere_files/icon_class_951819642.jpg" name="Registreringspliktig virksomhet" refid="ef0e2dfc-8346-4803-a917-50ff8895d0f1"/><isComposite humanName="Is Composite">false</isComposite><isDerived humanName="Is Derived" mode="s,e">false</isDerived><isDerivedUnion humanName="Is Derived Union" mode="e">false</isDerivedUnion><isID humanName="Is ID" mode="e">false</isID><isLeaf humanName="Is Leaf">false</isLeaf><isOrdered humanName="Is Ordered" mode="e">false</isOrdered><isReadOnly humanName="Is Read Only" mode="s,e">false</isReadOnly><isStatic humanName="Is Static" mode="s,e">false</isStatic><isUnique humanName="Is Unique" mode="e">true</isUnique><lower humanName="Lower">1</lower><multiplicity humanName="Multiplicity" mode="s,e"/><multiplicity humanName="Multiplicity" mode="s,e"/><name humanName="Name" mode="s,e"/><namespace classType="Class" humanName="Namespace" humanType="Class" icon="FOM-ReelleRettighetshavere_files/icon_class_951819642.jpg" name="Registreringspliktig virksomhet" refid="ef0e2dfc-8346-4803-a917-50ff8895d0f1"/><navigable humanName="Navigable" mode="e">true</navigable><opposite classType="Property" humanName="Opposite" humanType="Property" icon="FOM-ReelleRettighetshavere_files/icon_property_213290741.jpg" name=" : RegisterOverReelleRettighetshavere_fom::RegistreringspliktigVirksomhet::Registreringspliktig virksomhet" refid="a2b69749-5d0f-4b54-9edc-2ae64c292258"/><ownedBy classType="Class" humanName="Owned By" humanType="Class" icon="FOM-ReelleRettighetshavere_files/icon_class_951819642.jpg" mode="s,e" name="Registreringspliktig virksomhet" refid="ef0e2dfc-8346-4803-a917-50ff8895d0f1"/><owner classType="Class" humanName="Owner" humanType="Class" icon="FOM-ReelleRettighetshavere_files/icon_class_951819642.jpg" name="Registreringspliktig virksomhet" refid="ef0e2dfc-8346-4803-a917-50ff8895d0f1"/><qualifiedName humanName="Qualified Name" mode="e">RegisterOverReelleRettighetshavere_fom::RegistreringspliktigVirksomhet::Registreringspliktig virksomhet::</qualifiedName><redefinitionContext humanName="Redefinition Context"><class classType="Class" humanType="Class" icon="FOM-ReelleRettighetshavere_files/icon_class_951819642.jpg" name="Registreringspliktig virksomhet" refid="ef0e2dfc-8346-4803-a917-50ff8895d0f1"/></redefinitionContext><TO_DO humanName="To Do" mode="s,e"/><type classType="Class" humanName="Type" humanType="Class" icon="FOM-ReelleRettighetshavere_files/icon_class_951819642.jpg" mode="s,e" name="Utenlandsk virksomhet" refid="b75cc6cb-44db-4f53-8cff-c47b069e44b2"/><TYPE_MODIFIER humanName="Type Modifier" mode="e"/><upper humanName="Upper">1</upper><visibility humanName="Visibility" mode="s,e">private</visibility><appearsIn><diagram classType="Diagram" humanType="Diagram" icon="FOM-ReelleRettighetshavere_files/icon_Class Diagram_847518364.jpg" name="RegisterOverReelleRettighetshavere_fom" refid="b8a7e836-0572-48aa-82a4-fde8f46e38c3"/></appearsIn></property></magicdraw>